mangadex/__init__.py
mangadex/models.py
mangadexpy-0.3.2.dist-info/LICENSE
mangadexpy-0.3.2.dist-info/METADATA
mangadexpy-0.3.2.dist-info/WHEEL
mangadexpy-0.3.2.dist-info/top_level.txt
mangadexpy-0.3.2.dist-info/RECORD
