Metadata-Version: 2.1
Name: mangadexpy
Version: 0.3.2
Summary: Acts as a wrapper between you and mangadex's API, to allow easy integration. Probably sunsetted.
Home-page: https://repl.it/@thatonedev/mangadexpy
Author: thatonerandomdev
Author-email: no@u.net
License: UNKNOWN
Platform: UNKNOWN
Classifier: Programming Language :: Python :: 3
Classifier: License :: OSI Approved :: MIT License
Classifier: Operating System :: OS Independent
